{
  "updated": "2026-02-04T05:40:58.274077Z",
  "feeds": [
    {
      "source": "detik.com",
      "title": "Bamsoet Ingatkan Kepastian Hukum Jadi Kunci Keberhasilan Proyek Pemerintah"
    },
    {
      "source": "antaranews.com",
      "title": "Sebanyak 85.750 benih lobster senilai Rp4,3 miliar gagal diselundupkan ke Singapura"
    },
    {
      "source": "kompas.com",
      "title": "Kurangi Ketergantungan Impor Industri Kemasan, AKPI Investasi Rp 1,6 T"
    },
    {
      "source": "tempo.co",
      "title": "MUI: Prabowo Janji Keluar Dewan Perdamaian jika Tak Bawa Perubahan"
    },
    {
      "source": "republika.co.id",
      "title": "Tajir Sejati, Antara Aliran Sungai dan Aliran Rezeki"
    },
    {
      "source": "viva.co",
      "title": "Meski Sudah Ngaku dan Minta Maaf, Denada Belum Hubungi Ressa untuk Bertemu Langsung"
    },
    {
      "source": "jpnn.com",
      "title": "Bukan Sekadar Cuaca, Ini Hal yang Membuat Paulo Ricardo Betah di Persija Jakarta"
    },
    {
      "source": "times.co.id",
      "title": "Program Aspirasi Titiek Soeharto Hiadir di Gunungkidul, Petani Karangtengah Terima Ayam Petelur"
    },
    {
      "source": "BBC Indonesia",
      "title": "Yang perlu diketahui tentang RUU Pilkada"
    },
    {
      "source": "antaranews Jogja",
      "title": "KPK sebut persidangan ekstradisi Paulus Tannos sudah masuk babak akhir"
    }
  ]
}