{
  "updated": "2026-02-10T22:30:10.782391Z",
  "feeds": [
    {
      "source": "detik.com",
      "title": "Eks Bupati Bengkulu Utara Ditetapkan Tersangka Kasus Korupsi Tambang"
    },
    {
      "source": "antaranews.com",
      "title": "Westlife menyebut Indonesia sebagai \"rumah kedua\""
    },
    {
      "source": "kompas.com",
      "title": "Saling Kenal, Korban dan Pelaku Penusukan di Blok M Berdamai Usai Konflik Lahan Parkir"
    },
    {
      "source": "tempo.co",
      "title": "Pemerintah Reaktivasi Sementara 106 Ribu Peserta PBI BPJS"
    },
    {
      "source": "republika.co.id",
      "title": "Tawakal dalam Urusan Rezeki"
    },
    {
      "source": "viva.co",
      "title": "Tak Takut Dijebak Kasus Narkoba, Awkarin Langsung Tunjukkan Hasil Tes Urine"
    },
    {
      "source": "jpnn.com",
      "title": "Jadwal Lengkap Leg Pertama ACL 2: Hari Ini Persib Ingin Mengulang Memori Manis"
    },
    {
      "source": "BBC Indonesia",
      "title": "Yang perlu diketahui tentang RUU Pilkada"
    },
    {
      "source": "antaranews Jogja",
      "title": "Bernostalgia bersama Westlife dalam konser \"A Gala Evening\""
    }
  ]
}