{
  "updated": "2026-02-03T07:35:50.845694Z",
  "feeds": [
    {
      "source": "detik.com",
      "title": "BNN Bongkar 733 Kasus Narkoba di 2025, Sita 4 Ton Sabu hingga 4,7 Kg Kokain"
    },
    {
      "source": "antaranews.com",
      "title": "Mantan menteri kehakiman China dipenjara seumur hidup karena korupsi"
    },
    {
      "source": "kompas.com",
      "title": "Konsumsi Bubuk Elektrolit Saat Olahraga, Perlukah? Ini Kata Dokter"
    },
    {
      "source": "tempo.co",
      "title": "Bangunan Sekolah Garuda Ditargetkan Rampung Juni 2026"
    },
    {
      "source": "republika.co.id",
      "title": "Menteri LH Dorong Aksi Rumah Tangga Atasi Darurat Sampah Nasional"
    },
    {
      "source": "viva.co",
      "title": "BYD Siapkan Senjata Baru, Waktu Cas Dipangkas Brutal"
    },
    {
      "source": "jpnn.com",
      "title": "Seskab Teddy Bantah Perjalanan Luar Negeri Presiden Prabowo Pakai 2 Pesawat"
    },
    {
      "source": "times.co.id",
      "title": "Program Aspirasi Titiek Soeharto Hiadir di Gunungkidul, Petani Karangtengah Terima Ayam Petelur"
    },
    {
      "source": "BBC Indonesia",
      "title": "Yang perlu diketahui tentang RUU Pilkada"
    },
    {
      "source": "antaranews Jogja",
      "title": "Airlangga nilai penguatan IHSG Selasa didorong kembalinya dana asing"
    }
  ]
}