{
  "updated": "2026-02-07T12:26:06.058793Z",
  "feeds": [
    {
      "source": "detik.com",
      "title": "Mendagri: Bencana Banjir-Longsor Sumatera Beda dengan Tsunami Aceh 2004"
    },
    {
      "source": "antaranews.com",
      "title": "Trump siapkan tarif, ancam negara yang berbisnis dengan Iran"
    },
    {
      "source": "kompas.com",
      "title": "Hasil Persik vs Dewa United 2-1: Macan Putih Perkasa di Kandang"
    },
    {
      "source": "tempo.co",
      "title": "Gubernur NTT Ancam Pejabat yang Main-main Data Kemiskinan"
    },
    {
      "source": "republika.co.id",
      "title": "Keteladanan Jenderal Hoegeng, Sosok Kapolri yang Harum Namanya"
    },
    {
      "source": "viva.co",
      "title": "Tak Tayang di TV, Ini Link Live Streaming Duel Manchester United vs Tottenham yang Sedang Berlangsung"
    },
    {
      "source": "jpnn.com",
      "title": "Ekspansi Produk Premium di Indonesia, Haier Siap Pimpin Top Pasar Elektronik"
    },
    {
      "source": "times.co.id",
      "title": "Arah Baru Sepak Bola Indonesia: Pengembangan Pemain Muda dan Profesionalisme Liga"
    },
    {
      "source": "BBC Indonesia",
      "title": "Yang perlu diketahui tentang RUU Pilkada"
    },
    {
      "source": "antaranews Jogja",
      "title": "BTN gelar Run for Disabilitiesdi Solo"
    }
  ]
}